{"source":{"name":"Pacific Community (SPC) — Climate Change indicators","dataflow":"SPC:DF_CLIMATE_CHANGE(1.0)","hub":"Pacific Data Hub .Stat Explorer","url":"https://stats.pacificdata.org/","note":"Official Pacific Data Viz Challenge 2026 dataset. Annual, national-level observations.","geo":"PG","geo_name":"Papua New Guinea","extracted":"2026-07-06"},"oni_source":{"name":"Oceanic Niño Index (ONI) — NOAA Climate Prediction Center","url":"https://www.cpc.ncep.noaa.gov/products/analysis_monitoring/ensostuff/ONI_v5.php","note":"Peak ONI of the ENSO season developing in each year (Jun–Feb window) and the CPC episode classification. Transcribed table (see prep/README.md); the only series in the piece not from the SPC dataflow."},"years":[{"year":1979,"oni":0.6,"phase":"elnino","rain":-11.1,"driest":true},{"year":1980,"oni":-0.3,"phase":"neutral","rain":-2.8},{"year":1981,"oni":-0.1,"phase":"neutral","rain":5.9},{"year":1982,"oni":2.2,"phase":"elnino","rain":-17.7,"driest":true},{"year":1983,"oni":-0.9,"phase":"lanina","rain":13.1},{"year":1984,"oni":-1.1,"phase":"lanina","rain":4.5},{"year":1985,"oni":-0.5,"phase":"neutral","rain":10},{"year":1986,"oni":1.2,"phase":"elnino","rain":0.5},{"year":1987,"oni":1.7,"phase":"elnino","rain":-10,"driest":true},{"year":1988,"oni":-1.8,"phase":"lanina","rain":11.8},{"year":1989,"oni":0.1,"phase":"neutral","rain":3.4},{"year":1990,"oni":0.4,"phase":"neutral","rain":3.2},{"year":1991,"oni":1.7,"phase":"elnino","rain":-8.1,"driest":true},{"year":1992,"oni":0.2,"phase":"neutral","rain":-14.3,"driest":true},{"year":1993,"oni":0.1,"phase":"neutral","rain":-18.7,"driest":true},{"year":1994,"oni":1.1,"phase":"elnino","rain":-10.2,"driest":true},{"year":1995,"oni":-1,"phase":"lanina","rain":5},{"year":1996,"oni":-0.5,"phase":"neutral","rain":-2.8},{"year":1997,"oni":2.4,"phase":"elnino","rain":-26.7,"driest":true},{"year":1998,"oni":-1.6,"phase":"lanina","rain":12.3},{"year":1999,"oni":-1.7,"phase":"lanina","rain":7.4},{"year":2000,"oni":-0.7,"phase":"lanina","rain":5.5},{"year":2001,"oni":-0.1,"phase":"neutral","rain":6},{"year":2002,"oni":1.3,"phase":"elnino","rain":-5.4},{"year":2003,"oni":0.4,"phase":"neutral","rain":1.2},{"year":2004,"oni":0.7,"phase":"elnino","rain":-9.2,"driest":true},{"year":2005,"oni":-0.9,"phase":"lanina","rain":5.2},{"year":2006,"oni":0.9,"phase":"elnino","rain":1.3},{"year":2007,"oni":-1.6,"phase":"lanina","rain":4.9},{"year":2008,"oni":-0.8,"phase":"lanina","rain":9.6},{"year":2009,"oni":1.6,"phase":"elnino","rain":5.3},{"year":2010,"oni":-1.6,"phase":"lanina","rain":10.1},{"year":2011,"oni":-1.1,"phase":"lanina","rain":5.2},{"year":2012,"oni":-0.4,"phase":"neutral","rain":7.6},{"year":2013,"oni":-0.3,"phase":"neutral","rain":6.8},{"year":2014,"oni":0.6,"phase":"elnino","rain":-2.1},{"year":2015,"oni":2.6,"phase":"elnino","rain":-20.2,"driest":true},{"year":2016,"oni":-0.7,"phase":"lanina","rain":1.2},{"year":2017,"oni":-1,"phase":"lanina","rain":7},{"year":2018,"oni":0.9,"phase":"elnino","rain":-3.4},{"year":2019,"oni":0.5,"phase":"elnino","rain":22},{"year":2020,"oni":-1.3,"phase":"lanina","rain":-2.4},{"year":2021,"oni":-1,"phase":"lanina","rain":3.2},{"year":2022,"oni":-1,"phase":"lanina","rain":-6.4},{"year":2023,"oni":2,"phase":"elnino","rain":0.2},{"year":2024,"oni":-0.6,"phase":"lanina","rain":2.8},{"year":2025,"oni":null,"phase":"pending","rain":11.5}],"r_oni":-0.641,"r_local":0.482,"driest10":[{"year":1997,"phase":"elnino"},{"year":2015,"phase":"elnino"},{"year":1993,"phase":"neutral"},{"year":1982,"phase":"elnino"},{"year":1992,"phase":"neutral"},{"year":1979,"phase":"elnino"},{"year":1994,"phase":"elnino"},{"year":1987,"phase":"elnino"},{"year":2004,"phase":"elnino"},{"year":1991,"phase":"elnino"}],"driest_elnino_count":8,"mean_rain_elnino":-5.9,"mean_rain_other":3.5}